mockfirestore/__init__.py
mockfirestore/_helpers.py
mockfirestore/_transformations.py
mockfirestore/async_client.py
mockfirestore/client.py
mockfirestore/collection.py
mockfirestore/document.py
mockfirestore/exceptions.py
mockfirestore/query.py
mockfirestore/transaction.py
tests/__init__.py
tests/test_collection_reference.py
tests/test_document_reference.py
tests/test_document_snapshot.py
tests/test_mock_client.py
tests/test_timestamp.py
tests/test_transaction.py
firestore_mock-0.1.5.dist-info/LICENSE
firestore_mock-0.1.5.dist-info/METADATA
firestore_mock-0.1.5.dist-info/WHEEL
firestore_mock-0.1.5.dist-info/top_level.txt
firestore_mock-0.1.5.dist-info/RECORD
