Metadata-Version: 2.1
Name: firestore-mock
Version: 0.1.5
Summary: In-memory implementation of Google Cloud Firestore for use in tests with support for asyncio
Home-page: https://github.com/pckmsolutions/firestore-mock
Author: Peter Metcalf
Classifier: Programming Language :: Python :: 3.6
Classifier: Programming Language :: Python :: 3.7
Classifier: Programming Language :: Python :: 3.8
Classifier: Programming Language :: Python :: 3.9
Classifier: Programming Language :: Python :: 3.10
Classifier: License :: OSI Approved :: MIT License
License-File: LICENSE
